datadotworld/__init__.py
datadotworld/cli.py
datadotworld/config.py
datadotworld/datadotworld.py
datadotworld/files.py
datadotworld/util.py
datadotworld/client/__init__.py
datadotworld/client/api.py
datadotworld/client/content_negotiating_api_client.py
datadotworld/client/_swagger/__init__.py
datadotworld/client/_swagger/api_client.py
datadotworld/client/_swagger/configuration.py
datadotworld/client/_swagger/rest.py
datadotworld/client/_swagger/apis/__init__.py
datadotworld/client/_swagger/apis/connections_api.py
datadotworld/client/_swagger/apis/datasets_api.py
datadotworld/client/_swagger/apis/do_is_api.py
datadotworld/client/_swagger/apis/download_api.py
datadotworld/client/_swagger/apis/files_api.py
datadotworld/client/_swagger/apis/insights_api.py
datadotworld/client/_swagger/apis/metadataanalysis_api.py
datadotworld/client/_swagger/apis/metadatacollections_api.py
datadotworld/client/_swagger/apis/metadatadata_api.py
datadotworld/client/_swagger/apis/metadataglossary_api.py
datadotworld/client/_swagger/apis/metadataproperties_api.py
datadotworld/client/_swagger/apis/metadatarelationships_api.py
datadotworld/client/_swagger/apis/projects_api.py
datadotworld/client/_swagger/apis/queries_api.py
datadotworld/client/_swagger/apis/search_api.py
datadotworld/client/_swagger/apis/sparql_api.py
datadotworld/client/_swagger/apis/sql_api.py
datadotworld/client/_swagger/apis/streams_api.py
datadotworld/client/_swagger/apis/tables_api.py
datadotworld/client/_swagger/apis/uploads_api.py
datadotworld/client/_swagger/apis/user_api.py
datadotworld/client/_swagger/apis/users_api.py
datadotworld/client/_swagger/apis/webhooks_api.py
datadotworld/client/_swagger/models/__init__.py
datadotworld/client/_swagger/models/agent_hydration_dto.py
datadotworld/client/_swagger/models/analysis_image.py
datadotworld/client/_swagger/models/asset_status.py
datadotworld/client/_swagger/models/catalog_analysis_hydration_dto.py
datadotworld/client/_swagger/models/catalog_analysis_request.py
datadotworld-2.0.0.dist-info/LICENSE.txt
datadotworld-2.0.0.dist-info/METADATA
datadotworld-2.0.0.dist-info/WHEEL
datadotworld-2.0.0.dist-info/entry_points.txt
datadotworld-2.0.0.dist-info/top_level.txt
datadotworld-2.0.0.dist-info/RECORD
