Metadata-Version: 2.1
Name: datadotworld
Version: 2.0.0
Summary: Python library for data.world
Home-page: http://github.com/datadotworld/data.world-py
Author: data.world
Author-email: help@data.world
License: Apache 2.0
Keywords: data.world dataset
Classifier: Development Status :: 5 - Production/Stable
Classifier: Intended Audience :: Developers
Classifier: Intended Audience :: Science/Research
Classifier: License :: OSI Approved :: Apache Software License
Classifier: Operating System :: OS Independent
Classifier: Programming Language :: Python :: 3.9
Classifier: Programming Language :: Python :: 3.10
Classifier: Programming Language :: Python :: 3.11
Classifier: Programming Language :: Python :: 3.12
Classifier: Topic :: Database :: Database Engines/Servers
Classifier: Topic :: Scientific/Engineering :: Information Analysis
Classifier: Topic :: Software Development :: Libraries :: Python Modules
Requires-Python: >=3.9
License-File: LICENSE.txt
Requires-Dist: certifi>=2017.04.17
Requires-Dist: click<9.0a,>=8.0
Requires-Dist: configparser<4.0a,>=3.5.0
Requires-Dist: datapackage<2.0a,>=1.6.2
Requires-Dist: tableschema<2.0a,>=1.5.2
Requires-Dist: python-dateutil<3.0a,>=2.6.0
Requires-Dist: requests<3.0a,>=2.22.0
Requires-Dist: setuptools<70.0a,>=69.2.0
Requires-Dist: six<2.0a,>=1.5.0
Requires-Dist: tabulator>=1.22.0
Requires-Dist: urllib3<2.0a,>=1.15
Provides-Extra: pandas
Requires-Dist: numpy<=2.0a,>=1.26.4; extra == "pandas"
Requires-Dist: pandas<=1.3.5; extra == "pandas"
